qbank/__init__.py
qbank/utils.py
qbank/isq_nn/__init__.py
qbank/isq_nn/device_circuit8.isq
qbank/isq_nn/encoding.isq
qbank/isq_nn/unitary.isq
qbank/load/__init__.py
qbank/load/fea_load.py
qbank/sto_optimizer/__init__.py
qbank/sto_optimizer/spsa.py
qbank/train/__init__.py
qbank/train/data_train.py
qbank-0.1.0.dist-info/LICENSE.txt
qbank-0.1.0.dist-info/METADATA
qbank-0.1.0.dist-info/WHEEL
qbank-0.1.0.dist-info/top_level.txt
qbank-0.1.0.dist-info/RECORD
