Metadata-Version: 2.1
Name: qbank
Version: 0.1.0
Summary: A quantum machine learning package based isq
Author: cgl
Author-email: cgl <2082867125@qq.com>
License: GNU GENERAL PUBLIC LICENSE
Platform: python 3.8+
Classifier: Programming Language :: Python :: 3
Classifier: Operating System :: OS Independent
Requires-Python: >=3.8
License-File: LICENSE.txt
